{
    "miniprogramRoot": "dist/",
    "projectname": "myapp2",
    "description": "lucky demo",
    "appid": "wxe50bdd7c7bf5b815",
    "setting": {
        "urlCheck": true,
        "es6": false,
        "postcss": false,
        "minified": false,
        "babelSetting": {
            "ignore": [],
            "disablePlugins": [],
            "outputPath": ""
        }
    },
    "compileType": "miniprogram",
    "libVersion": "2.25.3",
    "srcMiniprogramRoot": "dist/",
    "packOptions": {
        "ignore": [],
        "include": []
    },
    "condition": {},
    "editorSetting": {
        "tabIndent": "insertSpaces",
        "tabSize": 4
    }
}